setup.py
scraperworldapi/main.py
scraperworldapi.egg-info/PKG-INFO
scraperworldapi.egg-info/SOURCES.txt
scraperworldapi.egg-info/dependency_links.txt
scraperworldapi.egg-info/top_level.txt