Metadata-Version: 2.1
Name: scraperworldapi
Version: 1.0
Summary: makes life easy
Author: bluesatan
License: MIT
Keywords: style
Classifier: Development Status :: 5 - Production/Stable
